disclog_burslf/__init__.py
disclog_burslf/disclog.py
disclog_burslf-0.0.5.dist-info/METADATA
disclog_burslf-0.0.5.dist-info/WHEEL
disclog_burslf-0.0.5.dist-info/top_level.txt
disclog_burslf-0.0.5.dist-info/RECORD
