Metadata-Version: 2.1
Name: disclog-burslf
Version: 0.0.5
Summary: A logging package that sends logs to Discord webhooks.
Author-email: Yoel <yoelz@tlvtech.io>
Classifier: License :: OSI Approved :: MIT License
Classifier: Programming Language :: Python :: 3.6
Classifier: Programming Language :: Python :: 3.7
Classifier: Programming Language :: Python :: 3.8
Classifier: Programming Language :: Python :: 3.9
Requires-Python: >=3.7
